{
    "configurations": [
        {
            "name": "Linux",
            "includePath": [
                "${workspaceFolder}/sources/app",
                "${workspaceFolder}/sources/externals",
                "/usr/include",
                "/usr/local/include"
            ],
            "defines": ["PLATFORMS_LINUX"],
            "compilerPath": "/usr/bin/g++",
            "cStandard": "c17",
            "cppStandard": "c++17",
            "intelliSenseMode": "linux-gcc-x64"
        },
        {
            "name": "Windows",
            "includePath": [
                "${workspaceFolder}\\sources\\app",
                "${workspaceFolder}\\sources\\externals",
            ],
            "defines": [
                "_WIN32", "PLATFORMS_WINDOWS"
            ],
            "compilerPath": "C:/MinGW/bin/g++.exe",
            "cStandard": "c17",
            "cppStandard": "c++17",
            "intelliSenseMode": "windows-gcc-x64"
        },
        {
            "name": "macOS",
            "includePath": [
                "${workspaceFolder}/sources/app",
                "${workspaceFolder}/sources/externals",
                "/usr/include",
                "/usr/local/include"
            ],
            "defines": ["PLATFORMS_MACOS"],
            "compilerPath": "/usr/bin/clang++",
            "cStandard": "c17",
            "cppStandard": "c++17",
            "intelliSenseMode": "macos-clang-x64"
        }
    ],
    "version": 4
}